{
    "global": {
        "description": "View the entire Coastal Resilience network of tools and information around the globe.",
        "url": "http://global.coastalresilience.org"
    },

    "regions": [
        {
            "name": "Caribbean",
            "description": "",
            "thumbnailUrl": "",
            "location": [-73.6, 17.3],
            "regions": [
                {
                    "name": "St. Vincent and the Grenadines/ Grenada",
                    "description": "",
                    "url": "",
                    "thumbnailUrl": ""
                },
                {
                    "name": "U.S. Virgin Islands",
                    "description": "",
                    "url": "",
                    "thumbnailUrl": ""
                },
                {
                    "name": "Mesoamerican Reef",
                    "description": "",
                    "url": "",
                    "thumbnailUrl": ""
                }
            ]
        },
        {
            "name": "Gulf of Mexico",
            "description": "",
            "thumbnailUrl": "",
            "location": [-91.1, 28.8],
            "regions": [
                {
                    "name": "Florida",
                    "description": "",
                    "thumbnailUrl": "",
                    "regions": [
                        {
                            "name": "Florida Keys",
                            "description": "",
                            "url": "",
                            "thumbnailUrl": ""
                        },
                        {
                            "name": "Charlotte Harbor",
                            "description": "",
                            "url": "",
                            "thumbnailUrl": ""
                        }
                    ]
                },
                {
                    "name": "Texas",
                    "description": "",
                    "thumbnailUrl": "",
                    "regions": [
                        {
                            "name": "Galveston Bay",
                            "description": "",
                            "url": "",
                            "thumbnailUrl": ""
                        }
                    ]
                }
            ]
        },
        {
            "name": "U.S. East Coast",
            "description": "",
            "thumbnailUrl": "",
            "location": [-70.8, 41.8],
            "regions": [
                {
                    "name": "New York and Connecticut (Long Island Sound)",
                    "description": "",
                    "url": "",
                    "thumbnailUrl": ""
                }
            ]
        },
        {
            "name": "U.S. West Coast",
            "description": "",
            "thumbnailUrl": "",
            "location": [-122.2, 37.2],
            "regions": [
                {
                    "name": "California",
                    "description": "",
                    "thumbnailUrl": "",
                    "regions": [
                        {
                            "name": "Ventura County",
                            "description": "",
                            "url": "",
                            "thumbnailUrl": ""
                        }
                    ]
                },
                {
                    "name": "Washington",
                    "description": "",
                    "thumbnailUrl": "",
                    "regions": [
                        {
                            "name": "Puget Sound",
                            "description": "",
                            "url": "",
                            "thumbnailUrl": ""
                        }
                    ]
                }
            ]
        },
        {
            "name": "Baja California",
            "description": "",
            "thumbnailUrl": "",
            "location": [-114.3, 28.7],
            "regions": [
                {
                    "name": "Baja California",
                    "description": "",
                    "url": "",
                    "thumbnailUrl": ""
                }
            ]
        }
    ]
}